db2ixf/__init__.py
db2ixf/_version.py
db2ixf/cli.py
db2ixf/collectors.py
db2ixf/constants.py
db2ixf/encoders.py
db2ixf/exceptions.py
db2ixf/helpers.py
db2ixf/ibmcodecs.py
db2ixf/ixf.py
db2ixf/logger.py
db2ixf-0.16.1.dist-info/LICENSE
db2ixf-0.16.1.dist-info/METADATA
db2ixf-0.16.1.dist-info/WHEEL
db2ixf-0.16.1.dist-info/entry_points.txt
db2ixf-0.16.1.dist-info/top_level.txt
db2ixf-0.16.1.dist-info/RECORD
