Metadata-Version: 2.1
Name: db2ixf
Version: 0.16.1
Summary: Parsing and processing of IBM eXchange format (IXF)
Author-email: Ismail Hammounou <ismail.hammounou@gmail.com>
Maintainer-email: Ismail Hammounou <ismail.hammounou@gmail.com>
License: AGPL-3.0
Project-URL: Changelog, https://github.com/ismailhammounou/db2ixf/blob/main/CHANGELOG.md
Project-URL: Documentation, https://ismailhammounou.github.io/db2ixf/
Project-URL: Homepage, https://pypi.org/project/db2ixf/
Project-URL: Repository, https://github.com/ismailhammounou/db2ixf.git
Keywords: PC,IXF,IBM,DB2,Development,Tools,Package,Parsing,Format,Data,Analysis
Classifier: Development Status :: 3 - Alpha
Classifier: Intended Audience :: Developers
Classifier: License :: OSI Approved :: GNU Affero General Public License v3
Classifier: Programming Language :: Python :: 3.8
Classifier: Programming Language :: Python :: 3.9
Classifier: Programming Language :: Python :: 3.10
Classifier: Programming Language :: Python :: 3.11
Requires-Python: >=3.8
License-File: LICENSE
Requires-Dist: ebcdic
Requires-Dist: pyarrow
Requires-Dist: deltalake
Requires-Dist: chardet
Requires-Dist: typer[all]
